CANgSnd/CANgSend.py
CANgSnd/__init__.py
CANgSnd/version.py
CANgSend-0.0.1.dist-info/LICENSE
CANgSend-0.0.1.dist-info/METADATA
CANgSend-0.0.1.dist-info/WHEEL
CANgSend-0.0.1.dist-info/top_level.txt
CANgSend-0.0.1.dist-info/RECORD
